scatter_letters/__init__.py
scatter_letters/masks.pkl
scatter_letters/sl.py
scatter_letters-0.0.7.dist-info/LICENSE.md
scatter_letters-0.0.7.dist-info/METADATA
scatter_letters-0.0.7.dist-info/WHEEL
scatter_letters-0.0.7.dist-info/top_level.txt
scatter_letters-0.0.7.dist-info/RECORD
