Metadata-Version: 2.1
Name: scatter-letters
Version: 0.0.7
Summary: A script to write letters with Matplotlib's scatter plots, create transitions from one plot to the other and build a GIF.
Home-page: https://github.com/Thiagobc23/Scatter-Letters
Author: Thiago B Carvalho
License: MIT
Platform: UNKNOWN
Classifier: Programming Language :: Python :: 3
Classifier: License :: OSI Approved :: MIT License
